vdg/__init__.py
vdg/autopub.py
vdg/draftgen.py
vdg/filters.py
vdg/main.py
vdg/utils.py
vdg/templates/bangumi.html.jinja
vdg/templates/bangumi.title.txt.jinja
vdg/templates/form.yml
vdg/templates/vcb-s.html.jinja
vdg/templates/vcb-s.title.txt.jinja
vdg-0.4.1.dist-info/LICENSE
vdg-0.4.1.dist-info/METADATA
vdg-0.4.1.dist-info/WHEEL
vdg-0.4.1.dist-info/entry_points.txt
vdg-0.4.1.dist-info/top_level.txt
vdg-0.4.1.dist-info/RECORD
