Metadata-Version: 2.1
Name: vdg
Version: 0.4.1
Summary: VCB-Studio 发布工具
Author: diazchika
Project-URL: Homepage, https://github.com/diazchika/vdg
Classifier: Development Status :: 4 - Beta
Classifier: License :: OSI Approved :: MIT License
Classifier: Programming Language :: Python :: 3.11
Requires-Python: >=3.11
License-File: LICENSE
Requires-Dist: selenium~=4.24.0
Requires-Dist: PyYAML~=6.0.2
Requires-Dist: html2text~=2024.2.26
Requires-Dist: Jinja2~=3.1.4
Provides-Extra: dev
Requires-Dist: setuptools; extra == "dev"
Requires-Dist: wheel; extra == "dev"
Requires-Dist: build; extra == "dev"
